conssert
