Metadata-Version: 1.1
Name: conssert
Version: 0.2.11
Summary: Content assertion library for Python
Home-page: https://github.com/podio/conssert
Author: Juan Alvarez
Author-email: juan.afernandez@ymail.com
License: UNKNOWN
Download-URL: https://github.com/podio/conssert/tarball/0.2.11
Keywords: validation,test,unit test,content assertion
Platform: any
Classifier: Development Status :: 4 - Beta
Classifier: Intended Audience :: Developers
Classifier: Operating System :: OS Independent
Classifier: Programming Language :: Python :: 2.7
Classifier: Topic :: Software Development :: Libraries :: Python Modules
Classifier: License :: OSI Approved :: MIT License
